IB/__init__.py
ib_cp_gateway-1.0.1.dist-info/LICENSE
ib_cp_gateway-1.0.1.dist-info/METADATA
ib_cp_gateway-1.0.1.dist-info/WHEEL
ib_cp_gateway-1.0.1.dist-info/top_level.txt
ib_cp_gateway-1.0.1.dist-info/RECORD
