Metadata-Version: 2.1
Name: ib-cp-gateway
Version: 1.0.1
Summary: This is a simple IB Client Portal Gateway RESTFul api, IB Client Portal Gateway can be run on Raspberry Pi or any other ARM machine(IB Gateway and TWS are not able to run on ARM).
Home-page: https://github.com/Iceloof/IB-ClientPortal-Gateway
Author: Hurin Hu
Author-email: hurin@live.ca
Classifier: Programming Language :: Python :: 3
Classifier: License :: OSI Approved :: MIT License
Classifier: Operating System :: OS Independent
Requires-Python: >=3.6
License-File: LICENSE
Requires-Dist: urllib3
Requires-Dist: requests
